{
    "title": "Quick to Assemble by kathy ireland,  Office Bush Furniture",
    "description": "Bush's QTA or Quick-to-Assemble technology allows you to build your furniture three-to-five times faster than traditional ready-to-assemble or for a lot less cost than expensive case good furniture.",
    "referenceId": "JGFpBB1sLq4",
    "date_created": "1505239609",
    "date_modified": "1505239609",
    "tags": null,
    "sourceId": "4",
    "status": "approved",
    "visibility": "1",
    "VV_VI": null,
    "engagement_score": null,
    "conversion_score": null,
    "CVV_VI": null,
    "classification": null,
    "id": "117459392",
    "loginId": "1759034",
    "entityType": "1",
    "titleTextEncoded": "Quick-to-Assemble-by-kathy-ireland-Office-Bush-Furniture",
    "category": null,
    "tvp_profiles": [
        "25",
        "18",
        "11"
    ],
    "tvp_profiles_manual": null,
    "tvp_profiles_maxscore": 6429.443,
    "VIDEO_LENGTH": "SHORT",
    "duration": 116,
    "settings": null,
    "asset": {
        "type": "youtube",
        "author": "Doc Strange",
        "hdvFlag": 1,
        "description": "Bush's QTA or Quick-to-Assemble technology allows you to build your furniture three-to-five times faster than traditional ready-to-assemble or for a lot less cost than expensive case good furniture.",
        "tags": "",
        "thumbnailUrl": "https:\/\/i.ytimg.com\/vi\/JGFpBB1sLq4\/maxresdefault.jpg",
        "videoId": "JGFpBB1sLq4",
        "mediaDuration": 116,
        "prettyDuration": "00:01:56"
    },
    "transcripts": null,
    "metrics_statistics": null
}