{
    "title": "iPad Air 2: White (Silver) vs Gold vs Black (Space Gray)",
    "description": "Apple iPad Air 2 comparison between the new Gold, Silver, and Space Gray with initial impressions! Which one should you choose?\n\niPhone 6 Plus Colors: http:\/\/youtu.be\/hi_eY1CPafw\n\nOur website: http:\/\/www.dargadgetz.com\nMy Tech\/Video Gear: http:\/\/amzn.to\/Y6CIJ5\n\nApp Reviewing Channel: http:\/\/www.youtube.com\/appquest\nTwitter: http:\/\/www.twitter.com\/dargadgetz\nGoogle+: http:\/\/goo.gl\/jy4Bf\nInstagram: dargadgetz\nFacebook: http:\/\/www.facebook.com\/dargadgetz\n\nIntro Song: OVERWERK - 12:30",
    "referenceId": "31cq3wDN28o",
    "date_created": "1505244019",
    "date_modified": "1505244019",
    "tags": null,
    "sourceId": "4",
    "status": "approved",
    "visibility": "1",
    "VV_VI": null,
    "engagement_score": null,
    "conversion_score": null,
    "CVV_VI": null,
    "classification": null,
    "id": "117461561",
    "loginId": "1759034",
    "entityType": "1",
    "titleTextEncoded": "iPad-Air-2-White-Silver-vs-Gold-vs-Black-Space-Gray",
    "category": null,
    "tvp_profiles": [
        "11"
    ],
    "tvp_profiles_manual": null,
    "tvp_profiles_maxscore": 10625.718,
    "VIDEO_LENGTH": "LONG",
    "duration": 416,
    "settings": null,
    "asset": {
        "type": "youtube",
        "author": "Daniel Romero",
        "hdvFlag": 1,
        "description": "Apple iPad Air 2 comparison between the new Gold, Silver, and Space Gray with initial impressions! Which one should you choose?\n\niPhone 6 Plus Colors: http:\/\/youtu.be\/hi_eY1CPafw\n\nOur website: http:\/\/www.dargadgetz.com\nMy Tech\/Video Gear: http:\/\/amzn.to\/Y6CIJ5\n\nApp Reviewing Channel: http:\/\/www.youtube.com\/appquest\nTwitter: http:\/\/www.twitter.com\/dargadgetz\nGoogle+: http:\/\/goo.gl\/jy4Bf\nInstagram: dargadgetz\nFacebook: http:\/\/www.facebook.com\/dargadgetz\n\nIntro Song: OVERWERK - 12:30",
        "tags": "",
        "thumbnailUrl": "https:\/\/i.ytimg.com\/vi\/31cq3wDN28o\/maxresdefault.jpg",
        "videoId": "31cq3wDN28o",
        "mediaDuration": 416,
        "prettyDuration": "00:06:56"
    },
    "transcripts": null,
    "metrics_statistics": null
}