{
    "title": "ASUS VivoBook E403SA-US21 FHD lightweight Laptop",
    "description": "ASUS VivoBook E403SA-US21 14\" FHD lightweight Laptop, Intel Quad Core 4GB RAM, 128GB eMMC, Win10, Hairline brushed Metal\nASUS VivoBook E403SA-US21 review - http:\/\/amzn.to\/2bYaCyp\n\nThe VivoBook E403 has been completely redesigned to give you a luxurious and durable feel for your everyday laptop. ASUS VivoBook E403 gives you all the essentials you need for everyday computing. With its compact dimensions, streamlined curves, and brushed aluminum finish, VivoBook E403 provides you with an incredibly premium feel \u2013 far from what you'd expect for a value laptop. \n\nQuad Core CPU for Powerful Multitasking\nVivoBook E403 is equipped with an Intel Quad Core N3700 Processor, one of the most powerful Intel Braswell processors available. It\u2019s perfect for multitasking, powering through your office programs, and 1080P video streaming without any drop in frame rates or visual quality. This extremely power-efficient processor also lets you stay productive all day long.",
    "referenceId": "TVrjjaalyv8",
    "date_created": "1518738932",
    "date_modified": "1518738932",
    "tags": null,
    "sourceId": "4",
    "status": "approved",
    "visibility": "1",
    "VV_VI": null,
    "engagement_score": null,
    "conversion_score": null,
    "CVV_VI": null,
    "classification": null,
    "id": "150221857",
    "loginId": "1759034",
    "entityType": "1",
    "titleTextEncoded": "ASUS-VivoBook-E403SA-US21-FHD-lightweight-Laptop",
    "category": null,
    "tvp_profiles": null,
    "tvp_profiles_manual": null,
    "tvp_profiles_maxscore": null,
    "VIDEO_LENGTH": "SHORT",
    "duration": 123,
    "settings": null,
    "asset": {
        "type": "youtube",
        "author": "Electronics R",
        "hdvFlag": 1,
        "description": "ASUS VivoBook E403SA-US21 14\" FHD lightweight Laptop, Intel Quad Core 4GB RAM, 128GB eMMC, Win10, Hairline brushed Metal\nASUS VivoBook E403SA-US21 review - http:\/\/amzn.to\/2bYaCyp\n\nThe VivoBook E403 has been completely redesigned to give you a luxurious and durable feel for your everyday laptop. ASUS VivoBook E403 gives you all the essentials you need for everyday computing. With its compact dimensions, streamlined curves, and brushed aluminum finish, VivoBook E403 provides you with an incredibly premium feel \u2013 far from what you'd expect for a value laptop. \n\nQuad Core CPU for Powerful Multitasking\nVivoBook E403 is equipped with an Intel Quad Core N3700 Processor, one of the most powerful Intel Braswell processors available. It\u2019s perfect for multitasking, powering through your office programs, and 1080P video streaming without any drop in frame rates or visual quality. This extremely power-efficient processor also lets you stay productive all day long.",
        "tags": "",
        "thumbnailUrl": "https:\/\/i.ytimg.com\/vi\/TVrjjaalyv8\/maxresdefault.jpg",
        "videoId": "TVrjjaalyv8",
        "mediaDuration": 123,
        "prettyDuration": "00:02:03"
    },
    "transcripts": null,
    "metrics_statistics": null
}